cython_backend.cp313-win_amd64.pyd
sigcoeff/__init__.py
sigcoeff/cuda_backend.py
sigcoeff/cython_backend.c
sigcoeff/cython_backend.pyx
sigcoeff/sigcoeff.py
sigcoeff-1.0.1.dist-info/licenses/LICENSE
sigcoeff-1.0.1.dist-info/METADATA
sigcoeff-1.0.1.dist-info/WHEEL
sigcoeff-1.0.1.dist-info/top_level.txt
sigcoeff-1.0.1.dist-info/RECORD
