Metadata-Version: 2.4
Name: sigcoeff
Version: 1.0.1
Summary: Sparse signature coefficient computations via kernels
Home-page: https://github.com/daniil-shmelev/sigcoeff
Author: Daniil Shmelev
Author-email: daniil.shmelev23@imperial.ac.uk
Classifier: Development Status :: 4 - Beta
Classifier: Environment :: Win32 (MS Windows)
Classifier: Intended Audience :: Developers
Classifier: Intended Audience :: Financial and Insurance Industry
Classifier: Intended Audience :: Healthcare Industry
Classifier: Intended Audience :: Information Technology
Classifier: Intended Audience :: Science/Research
Classifier: License :: OSI Approved :: Apache Software License
Classifier: Natural Language :: English
Classifier: Operating System :: MacOS
Classifier: Operating System :: Microsoft :: Windows
Classifier: Operating System :: Unix
Classifier: Programming Language :: Python
Classifier: Programming Language :: Python :: Implementation :: CPython
Classifier: Topic :: Scientific/Engineering :: Information Analysis
Classifier: Topic :: Scientific/Engineering :: Mathematics
License-File: LICENSE
Requires-Dist: torch>=2.4.1
Requires-Dist: numba>=0.60.0
Requires-Dist: cython>=3.0.11
Requires-Dist: numpy>=1.26.4
Requires-Dist: setuptools>=74.1.2
Provides-Extra: dev
Requires-Dist: check-manifest; extra == "dev"
Requires-Dist: twine; extra == "dev"
Requires-Dist: black; extra == "dev"
Dynamic: author
Dynamic: author-email
Dynamic: classifier
Dynamic: description
Dynamic: description-content-type
Dynamic: home-page
Dynamic: license-file
Dynamic: provides-extra
Dynamic: requires-dist
Dynamic: summary
